{
	"cmake" : 
	{
		"generator" : 
		{
			"multiConfig" : false,
			"name" : "Unix Makefiles"
		},
		"paths" : 
		{
			"cmake" : "/cygdrive/c/Users/ajays/AppData/Local/JetBrains/CLion2022.2/cygwin_cmake/bin/cmake.exe",
			"cpack" : "/cygdrive/c/Users/ajays/AppData/Local/JetBrains/CLion2022.2/cygwin_cmake/bin/cpack.exe",
			"ctest" : "/cygdrive/c/Users/ajays/AppData/Local/JetBrains/CLion2022.2/cygwin_cmake/bin/ctest.exe",
			"root" : "/cygdrive/c/Users/ajays/AppData/Local/JetBrains/CLion2022.2/cygwin_cmake/share/cmake-3.23.2"
		},
		"version" : 
		{
			"isDirty" : false,
			"major" : 3,
			"minor" : 23,
			"patch" : 2,
			"string" : "3.23.2",
			"suffix" : ""
		}
	},
	"objects" : 
	[
		{
			"jsonFile" : "codemodel-v2-c22c6f5d230fcf0fea1e.json",
			"kind" : "codemodel",
			"version" : 
			{
				"major" : 2,
				"minor" : 4
			}
		},
		{
			"jsonFile" : "cache-v2-223ed66776bfa0b98ec0.json",
			"kind" : "cache",
			"version" : 
			{
				"major" : 2,
				"minor" : 0
			}
		},
		{
			"jsonFile" : "cmakeFiles-v1-2a3776aa245d9dfa2684.json",
			"kind" : "cmakeFiles",
			"version" : 
			{
				"major" : 1,
				"minor" : 0
			}
		},
		{
			"jsonFile" : "toolchains-v1-2b88b02d7e12043bb487.json",
			"kind" : "toolchains",
			"version" : 
			{
				"major" : 1,
				"minor" : 0
			}
		}
	],
	"reply" : 
	{
		"cache-v2" : 
		{
			"jsonFile" : "cache-v2-223ed66776bfa0b98ec0.json",
			"kind" : "cache",
			"version" : 
			{
				"major" : 2,
				"minor" : 0
			}
		},
		"cmakeFiles-v1" : 
		{
			"jsonFile" : "cmakeFiles-v1-2a3776aa245d9dfa2684.json",
			"kind" : "cmakeFiles",
			"version" : 
			{
				"major" : 1,
				"minor" : 0
			}
		},
		"codemodel-v2" : 
		{
			"jsonFile" : "codemodel-v2-c22c6f5d230fcf0fea1e.json",
			"kind" : "codemodel",
			"version" : 
			{
				"major" : 2,
				"minor" : 4
			}
		},
		"toolchains-v1" : 
		{
			"jsonFile" : "toolchains-v1-2b88b02d7e12043bb487.json",
			"kind" : "toolchains",
			"version" : 
			{
				"major" : 1,
				"minor" : 0
			}
		}
	}
}
